facehuggershield/__init__.py
facehuggershield/huggingface/__init__.py
facehuggershield/huggingface/set_environment_variables.py
facehuggershield/huggingface/settings.py
facehuggershield-0.1.13.dist-info/licenses/LICENSE
facehuggershield-0.1.13.dist-info/METADATA
facehuggershield-0.1.13.dist-info/WHEEL
facehuggershield-0.1.13.dist-info/top_level.txt
facehuggershield-0.1.13.dist-info/RECORD
