Metadata-Version: 2.4
Name: facehuggershield
Version: 0.1.13
Home-page: https://github.com/Capsize-Games/facehuggershield
Author: Capsize LLC
Author-email: contact@capsizegames.com
License: GPL-3.0
Requires-Python: >=3.10.0
License-File: LICENSE
Requires-Dist: defendatron==0.1.11
Dynamic: author
Dynamic: author-email
Dynamic: description
Dynamic: description-content-type
Dynamic: home-page
Dynamic: keywords
Dynamic: license
Dynamic: license-file
Dynamic: requires-dist
Dynamic: requires-python
